pypsqueak/__init__.py
pypsqueak/errors.py
pypsqueak/gates.py
pypsqueak/api/__init__.py
pypsqueak/api/_helpers.py
pypsqueak/api/q_op.py
pypsqueak/api/q_oracle.py
pypsqueak/api/q_reg.py
pypsqueak/noise/__init__.py
pypsqueak/noise/_helpers.py
pypsqueak/noise/noise_maps.py
pypsqueak/noise/noise_model.py
pypsqueak/squeakcore/__init__.py
pypsqueak/squeakcore/_helpers.py
pypsqueak/squeakcore/gate.py
pypsqueak/squeakcore/qubit.py
pypSQUEAK-2.1.0.dist-info/LICENSE.txt
pypSQUEAK-2.1.0.dist-info/METADATA
pypSQUEAK-2.1.0.dist-info/WHEEL
pypSQUEAK-2.1.0.dist-info/top_level.txt
pypSQUEAK-2.1.0.dist-info/RECORD
