Metadata-Version: 2.1
Name: pypSQUEAK
Version: 2.1.0
Summary: A Python package for simulated quantum computing.
Home-page: https://github.com/jasonelhaderi/pypsqueak
Author: Jason K. Elhaderi
Author-email: jasonelhaderi@gmail.com
License: UNKNOWN
Platform: UNKNOWN
Classifier: Programming Language :: Python :: 3
Classifier: License :: OSI Approved :: MIT License
Classifier: Operating System :: OS Independent
Requires-Python: ~=3.8
Requires-Dist: numpy (>=1.19.1)
